odoo/addons/email_template_qweb/README.rst
odoo/addons/email_template_qweb/__init__.py
odoo/addons/email_template_qweb/__manifest__.py
odoo/addons/email_template_qweb/demo/ir_ui_view.xml
odoo/addons/email_template_qweb/demo/mail_template.xml
odoo/addons/email_template_qweb/i18n/de.po
odoo/addons/email_template_qweb/i18n/email_template_qweb.pot
odoo/addons/email_template_qweb/i18n/es.po
odoo/addons/email_template_qweb/i18n/es_MX.po
odoo/addons/email_template_qweb/i18n/fr.po
odoo/addons/email_template_qweb/i18n/fr_FR.po
odoo/addons/email_template_qweb/i18n/hr.po
odoo/addons/email_template_qweb/i18n/it.po
odoo/addons/email_template_qweb/i18n/nl_NL.po
odoo/addons/email_template_qweb/i18n/pt_BR.po
odoo/addons/email_template_qweb/i18n/zh_CN.po
odoo/addons/email_template_qweb/models/__init__.py
odoo/addons/email_template_qweb/models/mail_template.py
odoo/addons/email_template_qweb/readme/CONTRIBUTORS.rst
odoo/addons/email_template_qweb/readme/CREDITS.rst
odoo/addons/email_template_qweb/readme/DESCRIPTION.rst
odoo/addons/email_template_qweb/readme/USAGE.rst
odoo/addons/email_template_qweb/static/description/icon.png
odoo/addons/email_template_qweb/static/description/index.html
odoo/addons/email_template_qweb/tests/__init__.py
odoo/addons/email_template_qweb/tests/test_mail_template_qweb.py
odoo/addons/email_template_qweb/views/mail_template.xml
odoo_addon_email_template_qweb-16.0.1.0.0.11.dist-info/METADATA
odoo_addon_email_template_qweb-16.0.1.0.0.11.dist-info/WHEEL
odoo_addon_email_template_qweb-16.0.1.0.0.11.dist-info/top_level.txt
odoo_addon_email_template_qweb-16.0.1.0.0.11.dist-info/RECORD
